text2numb/__init__.py
text2numb-1.1.2.dist-info/LICENSE.txt
text2numb-1.1.2.dist-info/METADATA
text2numb-1.1.2.dist-info/WHEEL
text2numb-1.1.2.dist-info/top_level.txt
text2numb-1.1.2.dist-info/RECORD
