Metadata-Version: 2.1
Name: text2numb
Version: 1.1.2
Summary: Converts text into a numbers and back again. 
Author: Pigeon Nation
License: MIT
Classifier: Programming Language :: Python :: 3
Classifier: License :: OSI Approved :: MIT License
Classifier: Operating System :: OS Independent
Classifier: Topic :: Other/Nonlisted Topic
License-File: LICENSE.txt
